Workbook

Sheet Dashboard
A1: Sourcing Dashboard
A2: As of April 27, 2026 · Companies with 2+ data points only
B4: PIPELINE OVERVIEW
B5: Companies Tracked | C5: Total Candidates | D5: ⭐ Gold Companies | E5: Superstars | F5: Yes / Maybe / No
B6: =COUNTA(Rankings!B3:B5000) -> 832 | C6: =SUMIF(Rankings!B3:B5000,"<>",Rankings!D3:D5000) -> 10910 | D6: =COUNTIF(Rankings!E3:E5000,">"&2) -> 10 | E6: =SUM(Rankings!E3:E5000) -> 94 | F6: =SUM(Rankings!F3:F5000)&" / "&SUM(Rankings!G3:G5000)&" / "&SUM(Rankings!H3:H5000) -> 3481 / 1129 / 6206
B8: SOURCING HEALTH
B9: Overdue (>180d) | C9: Due Soon (90–180d) | D9: Fresh (<90d) | E9: Total Companies | F9: % Overdue
B10: =COUNTIF(Recency!D3:D5000,">"&180) -> 28 | C10: =COUNTIFS(Recency!D3:D5000,">"&90,Recency!D3:D5000,"<="&180) -> 20 | D10: =COUNTIF(Recency!D3:D5000,"<="&90) -> 286 | E10: =COUNTA(Recency!B3:B5000) -> 334 | F10: =IFERROR(COUNTIF(Recency!D3:D5000,">"&180)/COUNTA(Recency!B3:B5000),0) -> 0.083832335
B12: TOP 10 COMPANIES BY SCORE
B13: Company | C13: Score | D13: Superstars ★ | E13: Yes ✓ | F13: No ✗
B14: =IF(Rankings!E3>2,"⭐ ","")&Rankings!B3 -> ⭐ Palantir Technologies | C14: =Rankings!C3 -> 355 | D14: =Rankings!E3 -> 17 | E14: =Rankings!F3 -> 194 | F14: =Rankings!H3 -> 135
B15: =IF(Rankings!E4>2,"⭐ ","")&Rankings!B4 -> ⭐ Databricks | C15: =Rankings!C4 -> 149 | D15: =Rankings!E4 -> 3 | E15: =Rankings!F4 -> 109 | F15: =Rankings!H4 -> 116
B16: =IF(Rankings!E5>2,"⭐ ","")&Rankings!B5 -> ⭐ Glean | C16: =Rankings!C5 -> 137 | D16: =Rankings!E5 -> 3 | E16: =Rankings!F5 -> 81 | F16: =Rankings!H5 -> 48
B17: =IF(Rankings!E6>2,"⭐ ","")&Rankings!B6 -> ⭐ Meta | C17: =Rankings!C6 -> 124 | D17: =Rankings!E6 -> 16 | E17: =Rankings!F6 -> 336 | F17: =Rankings!H6 -> 759
B18: =IF(Rankings!E7>2,"⭐ ","")&Rankings!B7 -> Scale AI | C18: =Rankings!C7 -> 120 | D18: =Rankings!E7 -> 2 | E18: =Rankings!F7 -> 81 | F18: =Rankings!H7 -> 61
B19: =IF(Rankings!E8>2,"⭐ ","")&Rankings!B8 -> ⭐ xAI | C19: =Rankings!C8 -> 112 | D19: =Rankings!E8 -> 3 | E19: =Rankings!F8 -> 73 | F19: =Rankings!H8 -> 63
B20: =IF(Rankings!E9>2,"⭐ ","")&Rankings!B9 -> ⭐ Applied Intuition | C20: =Rankings!C9 -> 112 | D20: =Rankings!E9 -> 11 | E20: =Rankings!F9 -> 56 | F20: =Rankings!H9 -> 72
B21: =IF(Rankings!E10>2,"⭐ ","")&Rankings!B10 -> OpenAI | C21: =Rankings!C10 -> 105 | D21: =Rankings!E10 -> 1 | E21: =Rankings!F10 -> 77 | F21: =Rankings!H10 -> 60
B22: =IF(Rankings!E11>2,"⭐ ","")&Rankings!B11 -> Bloomberg | C22: =Rankings!C11 -> 75 | D22: =Rankings!E11 -> 0 | E22: =Rankings!F11 -> 50 | F22: =Rankings!H11 -> 45
B23: =IF(Rankings!E12>2,"⭐ ","")&Rankings!B12 -> Tesla | C23: =Rankings!C12 -> 75 | D23: =Rankings!E12 -> 0 | E23: =Rankings!F12 -> 66 | F23: =Rankings!H12 -> 72
B25: MOST OVERDUE — TOP SCORING
B26: Top scoring companies not sourced in 180+ days. Re-run script to refresh.
B27: Company | C27: Score | D27: Days Since Sourced | E27: # Candidates | F27: # Cohorts
B28: Icon | C28: 8 | D28: 204 | E28: 4 | F28: 1
B29: Abacus.AI | C29: 7 | D29: 375 | E29: 3 | F29: 1
B30: 1X | C30: 7 | D30: 248 | E30: 3 | F30: 3
B31: C3 AI | C31: 5 | D31: 182 | E31: 6 | F31: 5
B32: Deepnight (YC W24) | C32: 4 | D32: 212 | E32: 2 | F32: 1
B33: Reform | C33: 4 | D33: 262 | E33: 2 | F33: 2
B34: Sentry (sentry.io) | C34: 4 | D34: 196 | E34: 2 | F34: 2
B35: Aviator | C35: 4 | D35: 199 | E35: 2 | F35: 2
B36: Martin (YC S23) | C36: 4 | D36: 204 | E36: 2 | F36: 2
B37: Meticulate (YC W24) | C37: 3 | D37: 181 | E37: 2 | F37: 2
B39: 💡 KPIs in sections 1 & 2 auto-update via formulas. Re-run script to refresh Top 10 and Overdue after adding new data.

Sheet Rankings
A1: Company Rankings
A2: Rank | B2: Company | C2: Total Score | D2: Total Votes | E2: Superstar ★ | F2: Yes ✓ | G2: Maybe ? | H2: No ✗
A3: 1 | B3: Palantir Technologies | C3: 355 | D3: 363 | E3: 17 | F3: 194 | G3: 17 | H3: 135
A4: 2 | B4: Databricks | C4: 149 | D4: 260 | E4: 3 | F4: 109 | G4: 32 | H4: 116
A5: 3 | B5: Glean | C5: 137 | D5: 140 | E5: 3 | F5: 81 | G5: 8 | H5: 48
A6: 4 | B6: Meta | C6: 124 | D6: 1242 | E6: 16 | F6: 336 | G6: 131 | H6: 759
A7: 5 | B7: Scale AI | C7: 120 | D7: 153 | E7: 2 | F7: 81 | G7: 9 | H7: 61
A8: 6 | B8: xAI | C8: 112 | D8: 153 | E8: 3 | F8: 73 | G8: 14 | H8: 63 | M8: Graphite
A9: 7 | B9: Applied Intuition | C9: 112 | D9: 156 | E9: 11 | F9: 56 | G9: 17 | H9: 72 | M9: Retool
A10: 8 | B10: OpenAI | C10: 105 | D10: 144 | E10: 1 | F10: 77 | G10: 6 | H10: 60 | M10: Watershed
A11: 9 | B11: Bloomberg | C11: 75 | D11: 115 | E11: 0 | F11: 50 | G11: 20 | H11: 45 | M11: Warp
A12: 10 | B12: Tesla | C12: 75 | D12: 153 | E12: 0 | F12: 66 | G12: 15 | H12: 72 | M12: Foundry
A13: 11 | B13: Ramp | C13: 65 | D13: 77 | E13: 0 | F13: 44 | G13: 5 | H13: 28 | M13: Loop
A14: 12 | B14: Citadel | C14: 58 | D14: 82 | E14: 0 | F14: 42 | G14: 7 | H14: 33 | M14: Factory
A15: 13 | B15: Jane Street | C15: 56 | D15: 125 | E15: 1 | F15: 51 | G15: 11 | H15: 62 | M15: Merge
A16: 14 | B16: Figma | C16: 52 | D16: 167 | E16: 1 | F16: 65 | G16: 9 | H16: 92 | M16: Tennr (YC W23)
A17: 15 | B17: Google | C17: 49 | D17: 649 | E17: 0 | F17: 170 | G17: 94 | H17: 385 | M17: OpenEvidence
A18: 16 | B18: Anthropic | C18: 45 | D18: 105 | E18: 0 | F18: 46 | G18: 6 | H18: 53
A19: 17 | B19: Decagon | C19: 40 | D19: 25 | E19: 0 | F19: 21 | G19: 1 | H19: 3
A20: 18 | B20: Rox | C20: 35 | D20: 16 | E20: 4 | F20: 9 | G20: 0 | H20: 3
A21: 19 | B21: Google DeepMind | C21: 33 | D21: 72 | E21: 0 | F21: 27 | G21: 12 | H21: 33
A22: 20 | B22: Harvey | C22: 31 | D22: 27 | E22: 1 | F22: 14 | G22: 5 | H22: 7
A23: 21 | B23: Zip | C23: 31 | D23: 33 | E23: 3 | F23: 14 | G23: 2 | H23: 14
A24: 22 | B24: Notion | C24: 28 | D24: 52 | E24: 3 | F24: 18 | G24: 4 | H24: 27
A25: 23 | B25: SAIL | C25: 27 | D25: 68 | E25: 0 | F25: 31 | G25: 1 | H25: 36
A26: 24 | B26: Crusoe | C26: 27 | D26: 25 | E26: 0 | F26: 16 | G26: 2 | H26: 7
A27: 25 | B27: Stealth | C27: 27 | D27: 46 | E27: 1 | F27: 19 | G27: 5 | H27: 21
A28: 26 | B28: Graphite | C28: 24 | D28: 14 | E28: 0 | F28: 12 | G28: 1 | H28: 1
A29: 27 | B29: Roblox | C29: 23 | D29: 89 | E29: 0 | F29: 24 | G29: 20 | H29: 45
... A834: 832 | B834: Facebook | C834: -97 | D834: 143 | E834: 1 | F834: 0 | G834: 20 | H834: 122

Sheet Recency
A1: Re-Sourcing Tracker — Oldest First
A2: Rank | B2: Company | C2: Median Sourcing Date | D2: Days Ago | E2: # Candidates | F2: # Cohorts
A3: 1 | B3: Abacus.AI | C3: Apr 17, 2025 | D3: 375 | E3: 3 | F3: 1
A4: 2 | B4: OpenEvidence | C4: May 16, 2025 | D4: 345 | E4: 2 | F4: 1
A5: 3 | B5: Mistral AI | C5: Aug 01, 2025 | D5: 269 | E5: 3 | F5: 3 | L5: Re-Targeted
A6: 4 | B6: Reform | C6: Aug 08, 2025 | D6: 262 | E6: 2 | F6: 2
A7: 5 | B7: yondu | C7: Aug 12, 2025 | D7: 258 | E7: 2 | F7: 2 | L7: Kleiner Perkins | M7: 46089
A8: 6 | B8: YouTube | C8: Aug 21, 2025 | D8: 249 | E8: 3 | F8: 2 | L8: Perplexity | M8: 46089
A9: 7 | B9: 1X | C9: Aug 22, 2025 | D9: 248 | E9: 3 | F9: 3 | L9: Anysphere | M9: 46089
A10: 8 | B10: IXL Learning | C10: Aug 27, 2025 | D10: 243 | E10: 2 | F10: 1 | L10: Clay | M10: 46089
A11: 9 | B11: WeRide | C11: Sep 09, 2025 | D11: 229 | E11: 2 | F11: 2 | L11: Snorkel AI | M11: 46089
A12: 10 | B12: Labelbox | C12: Sep 15, 2025 | D12: 224 | E12: 2 | F12: 2 | L12: Jane Street | M12: 46089
A13: 11 | B13: Keystone AI | C13: Sep 17, 2025 | D13: 221 | E13: 2 | F13: 2 | L13: Two Sigma | M13: 46089
A14: 12 | B14: Remy | C14: Sep 18, 2025 | D14: 221 | E14: 2 | F14: 1 | L14: Five Rings | M14: 46089
A15: 13 | B15: Pinecone | C15: Sep 18, 2025 | D15: 220 | E15: 2 | F15: 1 | L15: Optiver | M15: 46089
A16: 14 | B16: GlossGenius | C16: Sep 20, 2025 | D16: 219 | E16: 2 | F16: 2 | L16: Jump Trading | M16: 46089
A17: 15 | B17: DALI Lab | C17: Sep 23, 2025 | D17: 216 | E17: 2 | F17: 2 | L17: Arrowstreet | M17: 46089
A18: 16 | B18: Deepnight (YC W24) | C18: Sep 27, 2025 | D18: 212 | E18: 2 | F18: 1 | L18: Vatic Labs | M18: 46089
A19: 17 | B19: Samsara | C19: Sep 28, 2025 | D19: 211 | E19: 3 | F19: 3 | L19: Hudston River Trading | M19: 46089
A20: 18 | B20: Niantic Inc. | C20: Oct 04, 2025 | D20: 205 | E20: 2 | F20: 2
A21: 19 | B21: Icon | C21: Oct 04, 2025 | D21: 204 | E21: 4 | F21: 1
A22: 20 | B22: Martin (YC S23) | C22: Oct 04, 2025 | D22: 204 | E22: 2 | F22: 2
A23: 21 | B23: Aviator | C23: Oct 09, 2025 | D23: 199 | E23: 2 | F23: 2
A24: 22 | B24: Sentry (sentry.io) | C24: Oct 12, 2025 | D24: 196 | E24: 2 | F24: 2
A25: 23 | B25: Gradient | C25: Oct 14, 2025 | D25: 194 | E25: 2 | F25: 2
A26: 24 | B26: Princeton Computer Science | C26: Oct 19, 2025 | D26: 190 | E26: 2 | F26: 2
A27: 25 | B27: Big Sur AI | C27: Oct 26, 2025 | D27: 182 | E27: 2 | F27: 2
A28: 26 | B28: C3 AI | C28: Oct 27, 2025 | D28: 182 | E28: 6 | F28: 5
A29: 27 | B29: Meticulate (YC W24) | C29: Oct 27, 2025 | D29: 181 | E29: 2 | F29: 2
A30: 28 | B30: 1stCollab (YC W23) | C30: Oct 28, 2025 | D30: 181 | E30: 2 | F30: 2
A31: 29 | B31: MosaicML | C31: Nov 02, 2025 | D31: 175 | E31: 2 | F31: 2
... A336: 334 | B336: Columbia University Department of Computer Science | C336: Apr 26, 2026 | D336: 1 | E336: 2 | F336: 2

Sheet Scoring Key
A1: Scoring System
A2: Calibration | B2: Points
A3: Superstar ★ | B3: +5
A4: Yes ✓ | B4: +2
A5: Maybe ? | B5: +1
A6: No ✗ | B6: -1
A8: Color Legend | B8: Criteria
A9: Gold | B9: > 2 Superstars
A10: Green | B10: Score ≥ 50 (no Gold)
A11: Blue | B11: Score ≥ 10 (no Gold/Green)
